bitprotolib/__init__.py
bitprotolib/bp.py
bitprotolib/py.typed
bitprotolib-0.1.0.dist-info/METADATA
bitprotolib-0.1.0.dist-info/WHEEL
bitprotolib-0.1.0.dist-info/top_level.txt
bitprotolib-0.1.0.dist-info/RECORD
