Metadata-Version: 2.1
Name: bitprotolib
Version: 0.1.0
Summary: bitproto encoding and decoding library for generated python files.
Home-page: https://github.com/hit9/bitproto
Author: Chao Wang
Author-email: hit9@icloud.com
License: UNKNOWN
Platform: any
Classifier: Development Status :: 2 - Pre-Alpha
Classifier: Environment :: Console
Classifier: Intended Audience :: Developers
Classifier: License :: OSI Approved :: BSD License
Classifier: Operating System :: OS Independent
Classifier: Programming Language :: Python
Classifier: Programming Language :: Python :: 3.7
Classifier: Programming Language :: Python :: 3.8
Classifier: Programming Language :: Python :: 3.9
Requires-Python: >=3.7
